taxation_properties_pkg/__init__.py
taxation_properties_pkg/taxation_properties.py
Taxation-0.0.2.dist-info/LICENCE.txt
Taxation-0.0.2.dist-info/METADATA
Taxation-0.0.2.dist-info/WHEEL
Taxation-0.0.2.dist-info/top_level.txt
Taxation-0.0.2.dist-info/RECORD
